Workbook

Sheet DCC I
A1: Exp. reclamo | B1: RESULTADO | C1: Tema | D1: Área de Origen | E1: Número de Resolución | F1: Sustento: Nulidad o Fundado | G1: Resolutor
A2: 4090340018142 | B2: NULIDAD | C2: Ajuste de valor | D2: Importaciones | E2: =+VLOOKUP(A2,[1]Producción!$H$1:$N$375,7,0) -> 4090140017687 | F2: No se analizó referencias | G2: Sanchez Torres Jorge Luis
A3: 4090340017717 | B3: FUNDADO | C3: Ajuste de valor | D3: Importaciones | E3: =+VLOOKUP(A3,[1]Producción!$H$1:$N$375,7,0) -> 4090140017484 | F3: Se utilizó una referencia invalida. No está dentro del margen de tolerancia | G3: Sanchez Torres Jorge Luis
A4: 4090340017774 | B4: FUNDADO | C4: Ajuste de valor | D4: Importaciones | E4: =+VLOOKUP(A4,[1]Producción!$H$1:$N$375,7,0) -> 4090140017507 | F4: Se utilizó una referencia invalida. No está dentro del margen de tolerancia | G4: Carbajal Jara Zaira
A5: 4090340017812 | B5: NULIDAD | C5: Devoluciones - TPI | D5: Recaudación | E5: =+VLOOKUP(A5,[1]Producción!$H$1:$N$375,7,0) -> 4090140017516 | F5: No se notifico el IDV que sustente el acto materia de impugnación. | G5: Cosio Jara Edgar Fernando
A6: 4090340017848 | B6: FUNDADO | C6: Devolución Ajuste de valor | D6: Recaudación | E6: =+VLOOKUP(A6,[1]Producción!$H$1:$N$375,7,0) -> 4090140017600 | F6: No evaluó doc. comercial | G6: Diaz Jurado Ana Maria
A7: 4090340017917 | B7: NULIDAD | C7: Ajuste de valor | D7: Importaciones | E7: =+VLOOKUP(A7,[1]Producción!$H$1:$N$375,7,0) -> 4090140017515 | F7: En el IDV se omitió analiza documentación contable presentada por el recurrente | G7: Sanchez Garrido Celso Felix
A8: 4090340017952 | B8: NULIDAD | C8: Ajuste de valor | D8: Importaciones | E8: =+VLOOKUP(A8,[1]Producción!$H$1:$N$375,7,0) -> 4090140017699 | F8: En el IDV se omitió analiza documentación contable presentada por el recurrente | G8: Vilcapaza Amaro Carla
A9: 4090340017961 | B9: NULIDAD | C9: Ajuste de valor | D9: Importaciones | E9: =+VLOOKUP(A9,[1]Producción!$H$1:$N$375,7,0) -> 4090140017581 | F9: En el IDV se omitió analiza documentación contable presentada por el recurrente | G9: Sanchez Garrido Celso Felix
A10: 4090340018014 | B10: NULIDAD | C10: Ajuste de valor | D10: Importaciones | E10: =+VLOOKUP(A10,[1]Producción!$H$1:$N$375,7,0) -> 4090140017664 | F10: En el IDV se omitió analiza documentación contable presentada por el recurrente | G10: Cordova Meza Luis Alberto
A11: 4090340018030 | B11: NULIDAD | C11: Ajuste de valor | D11: Importaciones | E11: =+VLOOKUP(A11,[1]Producción!$H$1:$N$375,7,0) -> 4090140017698 | F11: Referencia utilizada por la Administración se encuentra como valor en evaluación | G11: Quezada Villar Teresita Milagros
A12: 4090340018031 | B12: NULIDAD | C12: Ajuste de valor | D12: Importaciones | E12: =+VLOOKUP(A12,[1]Producción!$H$1:$N$375,7,0) -> 4090140017674 | F12: El IDV no realiza el analisis de idoneidad de todas las referencias presentadas por el recurrente | G12: Cordova Meza Luis Alberto
A13: 4090340018068 | B13: NULIDAD | C13: Ajuste de valor | D13: Importaciones | E13: =+VLOOKUP(A13,[1]Producción!$H$1:$N$375,7,0) -> 4090140017583 | F13: En el IDV se omitió analiza documentación contable presentada por el recurrente | G13: Sanchez Garrido Celso Felix
... A69: 4090340018834 | B69: NULIDAD | C69: Ajuste de valor | D69: Importaciones | E69: =+VLOOKUP(A69,[1]Producción!$H$1:$N$375,7,0) -> 4090140018052 | F69: No hubo pronunciamiento sobre expediente presentado | G69: Linares Alcantara Cesar Victor
